AUTHORS.rst
CONTRIBUTING.rst
HISTORY.rst
LICENSE
MANIFEST.in
README.rst
setup.cfg
setup.py
demo/manage.py
demo/demo/__init__.py
demo/demo/settings.py
demo/demo/urls.py
demo/demo/wsgi.py
pynt_of_django.egg-info/PKG-INFO
pynt_of_django.egg-info/SOURCES.txt
pynt_of_django.egg-info/dependency_links.txt
pynt_of_django.egg-info/not-zip-safe
pynt_of_django.egg-info/requires.txt
pynt_of_django.egg-info/top_level.txt
pyntofdjango/__init__.py
pyntofdjango/paths.py
pyntofdjango/project.py
pyntofdjango/tasks.py
pyntofdjango/tests.py
pyntofdjango/utils.py