Metadata-Version: 1.1
Name: pynt-of-django
Version: 0.3.2
Summary: A companion library for using pynt, a build tool, with Django projects.
Home-page: https://github.com/WimpyAnalytics/pynt-of-django
Author: Ivan Ven Osdel
Author-email: ivan@wimpyanalytics.com
License: BSD
Download-URL: https://github.com/wimpyanalytics/pynt-of-django/tarball/0.3.2
Keywords: pynt,django,build,make
Platform: UNKNOWN
Classifier: Development Status :: 5 - Production/Stable
Classifier: Intended Audience :: Developers
Classifier: License :: OSI Approved :: BSD License
Classifier: Natural Language :: English
Classifier: Programming Language :: Python :: 2.7
Classifier: Programming Language :: Python :: 3.6
